parse_dat_url/__init__.py
parse_dat_url-0.0.2.dist-info/METADATA
parse_dat_url-0.0.2.dist-info/WHEEL
parse_dat_url-0.0.2.dist-info/top_level.txt
parse_dat_url-0.0.2.dist-info/RECORD
