Metadata-Version: 2.1
Name: parse-dat-url
Version: 0.0.2
Summary: A small dat url parser package, still work in progree
Home-page: https://github.com/dryptomim/parse_dat_url
Author: Dryptomim
Author-email: dryptomim@arso.xyz
License: UNKNOWN
Platform: UNKNOWN
Classifier: Programming Language :: Python :: 3
Classifier: License :: OSI Approved :: MIT License
Classifier: Operating System :: OS Independent
Requires-Python: >=3.5
